[{"id":"1","title":"Spaghetti","url":"https://www.inspiredtaste.net/38940/spaghetti-with-meat-sauce-recipe/","tags":["italian","dinner"]},{"id":"2","title":"Avocado Toast","url":"https://cookieandkate.com/avocado-toast-recipe/","tags":["breakfast","vegetarian"]},{"id":"3","title":"Chicken Tikka Masala","url":"https://www.recipetineats.com/chicken-tikka-masala/","tags":["indian","spicy"]},{"id":"4","title":"Tacos al Pastor","url":"https://tastesbetterfromscratch.com/tacos-al-pastor/","tags":["mexican","street food"]},{"id":"5","title":"Sushi Roll","url":"https://www.fifteenspatulas.com/homemade-sushi/","tags":["japanese","seafood"]},{"id":"6","title":"Lasagna","url":"https://thecozycook.com/easy-lasagna-recipe/","tags":["italian","pasta","baked"]},{"id":"7","title":"Carbonara","url":"https://www.recipetineats.com/carbonara/","tags":["italian","pasta","eggs"]},{"id":"8","title":"Enchiladas Rojas","url":"https://www.muydelish.com/enchiladas-rojas/","tags":["mexican","spicy","cheesy"]},{"id":"9","title":"Pulled Pork Sandwich","url":"https://mytastytrials.com/2020/04/28/best-bbq-pulled-pork-sammies/","tags":["american","barbecue","slow-cooked"]},{"id":"10","title":"Chicken and Waffles","url":"https://www.sweetteaandthyme.com/fried-chicken-waffles-spicy-honey-sauce/","tags":["american","comfort","breakfast"]},{"id":"11","title":"Meatloaf","url":"https://natashaskitchen.com/meatloaf-recipe/","tags":["american","dinner","classic"]},{"id":"12","title":"Cornbread","url":"https://www.allrecipes.com/recipe/17891/golden-sweet-cornbread/","tags":["american","southern","bread"]}]